[
  {
    "title": "Dashboard",
    "link": "/",
    "name": "dashboard",
    "icon": "book-alt"
  },
  {
    "title": "Help",
    "link": "/help",
    "name": "help",
    "icon": "help-circle"
  },
  {
    "title": "Members",
    "link": "/members",
    "name": "members",
    "icon": "group"
  },
  {
    "title": "Payments",
    "link": "/payments",
    "name": "payments",
    "icon": "wallet"
  },
  {
    "title": "Localization",
    "link": "/localization",
    "name": "localization",
    "icon": "world"
  },
  {
    "title": "Settings",
    "link": "/settings",
    "name": "settings",
    "icon": "cog"
  },
  {
    "title": "Administration",
    "link": "/administration",
    "name": "administration",
    "icon": "slider"
  },
  {
    "title": "Statistics",
    "link": "/statistics",
    "name": "statistics",
    "icon": "line-chart"
  },
  {
    "title": "Blacklist",
    "link": "/blacklist",
    "name": "blacklist",
    "icon": "user"
  }
]